whylogs_provider/__init__.py
whylogs_provider/operators/__init__.py
whylogs_provider/operators/whylogs.py
airflow_provider_whylogs-0.0.3.dist-info/LICENSE
airflow_provider_whylogs-0.0.3.dist-info/METADATA
airflow_provider_whylogs-0.0.3.dist-info/WHEEL
airflow_provider_whylogs-0.0.3.dist-info/entry_points.txt
airflow_provider_whylogs-0.0.3.dist-info/top_level.txt
airflow_provider_whylogs-0.0.3.dist-info/RECORD
