Metadata-Version: 2.1
Name: airflow-provider-whylogs
Version: 0.0.3
Summary: An Apache Airflow provider for whylogs
Home-page: https://github.com/whylabs/airflow-provider-whylogs
Author: WhyLabs.ai
Requires-Python: >=3.7
License-File: LICENSE
Requires-Dist: apache-airflow >=2.0
Requires-Dist: whylogs[s3,viz] >=1.0.10
